Metadata-Version: 1.0
Name: ivanp
Version: 0.9
Summary: description on site https://ivanp-pip.online/
Home-page: UNKNOWN
Author: UNKNOWN
Author-email: ivan.buryy.19@mail.ru
License: UNKNOWN
Platform: UNKNOWN
